{"version":1,"resource":"file:///home/sumi/.config/i3blocks/config","entries":[{"id":"Jwp0","timestamp":1678291849453},{"id":"E3HP","timestamp":1678291911686},{"id":"eu4o","source":"undoRedo.source","timestamp":1678291923263},{"id":"Gave","timestamp":1678292003916},{"id":"EpL4","timestamp":1678292022016},{"id":"hhvH","timestamp":1678292059470},{"id":"jFAA","timestamp":1678292104720},{"id":"h4Le","timestamp":1678292144453},{"id":"174j","timestamp":1678292184410},{"id":"4mvD","timestamp":1678292234164},{"id":"vDbq","timestamp":1678292253347},{"id":"CThx","timestamp":1678292294421},{"id":"W6av","source":"undoRedo.source","timestamp":1678292310174},{"id":"hQeY","timestamp":1678292352784},{"id":"nloT","timestamp":1678292368754},{"id":"Inzf","source":"undoRedo.source","timestamp":1678292375128},{"id":"Rz3f","timestamp":1678292380098},{"id":"CVK9","timestamp":1678292401711},{"id":"qaJC","timestamp":1678292418298},{"id":"t8pF","timestamp":1678292441498},{"id":"VviH","timestamp":1678292903163},{"id":"Bd7c","timestamp":1678292942154},{"id":"jA90","timestamp":1678292958764},{"id":"GIVI","timestamp":1678292974474},{"id":"g0cx","timestamp":1678292993334},{"id":"Mw53","source":"undoRedo.source","timestamp":1678293001437},{"id":"l4Wd","timestamp":1678293018631},{"id":"hyqY","timestamp":1678293040384},{"id":"zYDB","timestamp":1678293051794},{"id":"edjx","timestamp":1678293065621},{"id":"8UIE","timestamp":1678293127327},{"id":"C7ue","timestamp":1678293148934},{"id":"75MR","timestamp":1678293173421},{"id":"ltgv","timestamp":1678293202091},{"id":"eER6","timestamp":1678293217851},{"id":"gqnh","timestamp":1678293252518},{"id":"lNWS","source":"undoRedo.source","timestamp":1678293255381},{"id":"WtoE","timestamp":1678293315421},{"id":"DWvR","timestamp":1678293330385},{"id":"FrNi","timestamp":1678293368712},{"id":"n7yQ","timestamp":1678293381262},{"id":"7Daz","timestamp":1678293396778},{"id":"aQ4i","timestamp":1678293432982},{"id":"ERuL","timestamp":1678293468632},{"id":"OOUT","timestamp":1678293485956},{"id":"ZM3V","timestamp":1678293529769},{"id":"lXpT","timestamp":1678293545473},{"id":"bc9f","timestamp":1678293629840},{"id":"Q8cF","timestamp":1678293681210},{"id":"Y6DN","timestamp":1678293736237}]}